magma_var/__init__.py
magma_var/const.py
magma_var/download.py
magma_var/earthquakes.py
magma_var/magma_var.py
magma_var/plot.py
magma_var/utils.py
magma_var-0.1.0.dist-info/licenses/LICENSE
magma_var-0.1.0.dist-info/WHEEL
magma_var-0.1.0.dist-info/METADATA
magma_var-0.1.0.dist-info/RECORD
