Metadata-Version: 2.4
Name: magma-var
Version: 0.1.0
Summary: MAGMA Volcanic Activity Report (VAR)
Keywords: magma,indonesia,volcano,volcanoes
Author-email: Martanto <martanto@live.com>, Devy Kamil Syahbana <devy.syahbana@gmail.com>, Syarif Abdul Manaf <riefmof@gmail.com>
Requires-Python: >=3.11
Classifier: License :: OSI Approved :: MIT License
Classifier: Operating System :: OS Independent
Classifier: Programming Language :: Python :: 3.11
Classifier: Programming Language :: Python :: 3.12
License-File: LICENSE
Requires-Dist: openpyxl>=3.1.5
Requires-Dist: pandas>=2.2.2
Requires-Dist: numpy>=2.2.5
Requires-Dist: matplotlib>=3.9.0
Requires-Dist: magma-database>=1.6.0
Requires-Dist: magma-auth
Requires-Dist: peewee>=3.17.5
Requires-Dist: black[d] ; extra == "dev"
Requires-Dist: isort ; extra == "dev"
Requires-Dist: openpyxl ; extra == "dev"
Requires-Dist: pandas ; extra == "dev"
Requires-Dist: numpy ; extra == "dev"
Requires-Dist: matplotlib ; extra == "dev"
Requires-Dist: magma-database ; extra == "dev"
Requires-Dist: peewee ; extra == "dev"
Requires-Dist: material-color ; extra == "dev"
Project-URL: Homepage, https://github.com/martanto/magma-var
Project-URL: Issues, https://github.com/martanto/magma-var/issues
Provides-Extra: dev
